event_external_local/__init__.py
event_external_local/event_external.py
event_external_local/event_external_constants.py
event_external_local/event_external_local.py
event_external_local-0.0.22.dist-info/METADATA
event_external_local-0.0.22.dist-info/WHEEL
event_external_local-0.0.22.dist-info/top_level.txt
event_external_local-0.0.22.dist-info/RECORD
