Metadata-Version: 2.1
Name: event-external-local
Version: 0.0.22
Summary: PyPI Package for Circles event-external-local Python
Home-page: https://github.com/circles-zone/event-external-local-python-package
Author: Circles
Author-email: info@circlez.ai
Classifier: Programming Language :: Python :: 3
Classifier: License :: Other/Proprietary License
Classifier: Operating System :: OS Independent
Requires-Dist: logger-local >=0.0.135
Requires-Dist: database-mysql-local >=0.0.290
Requires-Dist: python-sdk-remote >=0.0.93
